configparser_crypt/__init__.py
configparser_crypt/dict_convert.py
configparser_crypt-1.1.0.dist-info/LICENSE
configparser_crypt-1.1.0.dist-info/METADATA
configparser_crypt-1.1.0.dist-info/WHEEL
configparser_crypt-1.1.0.dist-info/top_level.txt
configparser_crypt-1.1.0.dist-info/RECORD
